fairways/__init__.py
fairways/app.py
fairways/conf.py
fairways/dynload.py
fairways/funcflow.py
fairways/helpers.py
fairways/log.py
fairways/taskflow.py
fairways/ci/__init__.py
fairways/ci/fakedb.py
fairways/ci/helpers.py
fairways/ci/influx_observer.py
fairways/ci/observer.py
fairways/ci/utils.py
fairways/ci/templates/__init__.py
fairways/ci/templates/fixture_template.py
fairways/decorators/__init__.py
fairways/decorators/apitag.py
fairways/decorators/asyncmethod.py
fairways/decorators/config.py
fairways/decorators/connection.py
fairways/decorators/entities.py
fairways/decorators/entrypoint.py
fairways/decorators/overload.py
fairways/decorators/typecast.py
fairways/decorators/use.py
fairways/io/__init__.py
fairways/io/asyn/__init__.py
fairways/io/asyn/amqp.py
fairways/io/asyn/base.py
fairways/io/asyn/mysql.py
fairways/io/asyn/redis.py
fairways/io/asyn/sqlite.py
fairways/io/generic/__init__.py
fairways/io/generic/base.py
fairways/io/generic/dbi.py
fairways/io/generic/net.py
fairways/io/generic/serde.py
fairways/io/syn/__init__.py
fairways/io/syn/amqp.py
fairways/io/syn/base.py
fairways/io/syn/cassandra.py
fairways/io/syn/csv.py
fairways/io/syn/generic_datastore.py
fairways/io/syn/http.py
fairways/io/syn/influx.py
fairways/io/syn/json.py
fairways/io/syn/mysql.py
fairways/io/syn/oracle.py
fairways/io/syn/pg.py
fairways/io/syn/redis.py
fairways/io/syn/sqlite.py
test/__init__.py
test/fixture_subject.py
test/test_asyn_loop.py
test/test_dbi.py
test/test_deco_api_tentative.py
test/test_decorators.py
test/test_decorators_async.py
test/test_decorators_conf.py
test/test_decorators_overload.py
test/test_decorators_typecast.py
test/test_entries_marks.py
test/test_env.py
test/test_examle_pool.py
test/test_ext_amqp_asyn.py
test/test_ext_amqp_syn.py
test/test_ext_cassandra_syn.py
test/test_ext_http.py
test/test_ext_influx.py
test/test_ext_mysql_syn.py
test/test_ext_oracle_syn.py
test/test_ext_redis.py
test/test_fixture_template.py
test/test_funcflow.py
test/test_helpers.py
fairways-0.9.13.dist-info/LICENSE
fairways-0.9.13.dist-info/LICENSE-APACHE
fairways-0.9.13.dist-info/LICENSE-MIT
fairways-0.9.13.dist-info/METADATA
fairways-0.9.13.dist-info/NOTICE.txt
fairways-0.9.13.dist-info/WHEEL
fairways-0.9.13.dist-info/top_level.txt
fairways-0.9.13.dist-info/RECORD
