Metadata-Version: 2.1
Name: fairways
Version: 0.9.13
Summary: Toolset to organize tasks
Home-page: https://gitlab.com/danwin/fairways_py#egg=fairways
Author: Dmitry Zimoglyadov
Author-email: dmitry.zimoglyadov@gmail.com
License: Apache 2.0 / MIT
Platform: UNKNOWN
Requires-Python: >=3.6
Requires-Dist: cached-property (>=1.5.1)
Requires-Dist: colorlog (>=4.0.2)
Requires-Dist: python-dateutil (>=2.8.0)
Requires-Dist: python-dotenv (>=0.10.3)
Requires-Dist: requests (>=2.22.0)
